whatthemullvad/__init__.py
whatthemullvad/checkproxy.py
whatthemullvad/main.py
whatthemullvad/mullvad_proxies_api.py
whatthemullvad-0.0.1.dist-info/METADATA
whatthemullvad-0.0.1.dist-info/WHEEL
whatthemullvad-0.0.1.dist-info/entry_points.txt
whatthemullvad-0.0.1.dist-info/licenses/LICENSE
whatthemullvad-0.0.1.dist-info/RECORD
