Metadata-Version: 2.4
Name: whatthemullvad
Version: 0.0.1
Summary: Test if Mullvad SOCKS5 proxies can access a given URL.
Project-URL: Homepage, https://gitlab.com/duinzand/whatthemullvad
Project-URL: Issues, https://gitlab.com/duinzand/whatthemullvad/-/issues
Author: Duinzand
License-Expression: AGPL-3.0-or-later
License-File: LICENSE
Classifier: Operating System :: OS Independent
Classifier: Programming Language :: Python :: 3
Requires-Python: >=3.9
Requires-Dist: requests
